namekoplus-0.5.3.dist-info/METADATA
namekoplus-0.5.3.dist-info/WHEEL
namekoplus-0.5.3.dist-info/entry_points.txt
namekoplus-0.5.3.dist-info/licenses/LICENSE
namekoplus/__init__.py
namekoplus/chassis-agent/__init__.py
namekoplus/chassis-agent/metric-configs/grafana.json.mako
namekoplus/chassis-agent/metric-configs/grafana_conf/config/grafana.ini
namekoplus/chassis-agent/metric-configs/grafana_conf/provisioning/dashboards/all.yaml
namekoplus/chassis-agent/metric-configs/grafana_conf/provisioning/datasources/all.yaml
namekoplus/chassis-agent/metric-configs/prometheus_conf/prometheus.yml
namekoplus/chassis-agent/metric-configs/statsd_config.js
namekoplus/chassis-agent/metric-configs/statsd_mapping.yml.mako
namekoplus/chassis-agent/rabbitmq/docker-compose-rabbitmq.yml
namekoplus/chassis/__init__.py
namekoplus/chassis/chassis.py
namekoplus/command.py
namekoplus/templates/__init__.py
namekoplus/templates/all/__init__.py
namekoplus/templates/all/all_demo.py
namekoplus/templates/all/config.yml
namekoplus/templates/demo/__init__.py
namekoplus/templates/demo/config.yml
namekoplus/templates/demo/rpc_demo.py
namekoplus/templates/event/__init__.py
namekoplus/templates/event/config.yml
namekoplus/templates/event/events_demo.py
namekoplus/templates/http/__init__.py
namekoplus/templates/http/config.yml
namekoplus/templates/http/http_demo.py
namekoplus/templates/rpc/__init__.py
namekoplus/templates/rpc/config.yml
namekoplus/templates/rpc/rpc_demo.py
namekoplus/templates/timer/__init__.py
namekoplus/templates/timer/config.yml
namekoplus/templates/timer/timer_demo.py
namekoplus/tests/__init__.py
namekoplus/tests/unit/__init__.py
namekoplus/tests/unit/test_service.py
namekoplus-0.5.3.dist-info/RECORD
